gmailsorter/__init__.py
gmailsorter/__main__.py
gmailsorter/_version.py
gmailsorter/local.py
gmailsorter/base/__init__.py
gmailsorter/base/database.py
gmailsorter/base/message.py
gmailsorter/daemon/__init__.py
gmailsorter/daemon/__main__.py
gmailsorter/daemon/daemon.py
gmailsorter/daemon/shared.py
gmailsorter/daemon/tasks.py
gmailsorter/google/__init__.py
gmailsorter/google/authentication.py
gmailsorter/google/database.py
gmailsorter/google/mail.py
gmailsorter/google/message.py
gmailsorter/ml/__init__.py
gmailsorter/ml/database.py
gmailsorter/ml/encoding.py
gmailsorter/ml/model.py
gmailsorter/webapp/__init__.py
gmailsorter/webapp/__main__.py
gmailsorter/webapp/app.py
gmailsorter/webapp/config.py
gmailsorter/webapp/database.py
gmailsorter/webapp/googleapi.py
gmailsorter/webapp/render.py
gmailsorter/webapp/user.py
gmailsorter/webapp/wsgi.py
gmailsorter/webapp/static/css/main.css
gmailsorter/webapp/static/css/util.css
gmailsorter/webapp/static/fonts/poppins/Poppins-Black.ttf
gmailsorter/webapp/static/fonts/poppins/Poppins-BlackItalic.ttf
gmailsorter/webapp/static/fonts/poppins/Poppins-Bold.ttf
gmailsorter/webapp/static/fonts/poppins/Poppins-BoldItalic.ttf
gmailsorter/webapp/static/fonts/poppins/Poppins-ExtraBold.ttf
gmailsorter/webapp/static/fonts/poppins/Poppins-ExtraBoldItalic.ttf
gmailsorter/webapp/static/fonts/poppins/Poppins-ExtraLight.ttf
gmailsorter/webapp/static/fonts/poppins/Poppins-ExtraLightItalic.ttf
gmailsorter/webapp/static/fonts/poppins/Poppins-Italic.ttf
gmailsorter/webapp/static/fonts/poppins/Poppins-Light.ttf
gmailsorter/webapp/static/fonts/poppins/Poppins-LightItalic.ttf
gmailsorter/webapp/static/fonts/poppins/Poppins-Medium.ttf
gmailsorter/webapp/static/fonts/poppins/Poppins-MediumItalic.ttf
gmailsorter/webapp/static/fonts/poppins/Poppins-Regular.ttf
gmailsorter/webapp/static/fonts/poppins/Poppins-SemiBold.ttf
gmailsorter/webapp/static/fonts/poppins/Poppins-SemiBoldItalic.ttf
gmailsorter/webapp/static/fonts/poppins/Poppins-Thin.ttf
gmailsorter-0.1.5.dist-info/METADATA
gmailsorter-0.1.5.dist-info/WHEEL
gmailsorter-0.1.5.dist-info/entry_points.txt
gmailsorter-0.1.5.dist-info/licenses/LICENSE
gmailsorter-0.1.5.dist-info/RECORD
