Metadata-Version: 2.4
Name: gmailsorter
Version: 0.1.5
Summary: Assign labels to emails in Google Mail based on their similarity to other emails assigned to the same label.
Project-URL: Homepage, https://github.com/jan-janssen/gmailsorter
Author-email: Jan Janssen <jan.janssen@outlook.com>
License-Expression: BSD-3-Clause
License-File: LICENSE
Classifier: Development Status :: 4 - Beta
Classifier: Intended Audience :: Science/Research
Classifier: License :: OSI Approved :: BSD License
Classifier: Operating System :: OS Independent
Classifier: Programming Language :: Python :: 3.8
Classifier: Programming Language :: Python :: 3.9
Classifier: Programming Language :: Python :: 3.10
Classifier: Programming Language :: Python :: 3.11
Classifier: Programming Language :: Python :: 3.12
Classifier: Programming Language :: Python :: 3.13
Requires-Python: >=3.8
Requires-Dist: google-api-python-client>=2.177.0
Requires-Dist: google-auth-oauthlib>=1.2.2
Requires-Dist: google-auth>=2.40.3
Requires-Dist: numpy>=2.2.4
Requires-Dist: pandas>=2.3.1
Requires-Dist: scikit-learn>=1.6.1
Requires-Dist: sqlalchemy>=2.0.42
Requires-Dist: tqdm>=4.67.1
Provides-Extra: webapp
Requires-Dist: flask-login>=0.6.3; extra == 'webapp'
Requires-Dist: flask>=3.1.1; extra == 'webapp'
Requires-Dist: gunicorn>=23.0.0; extra == 'webapp'
